deepbench/__init__.py
deepbench/astro_object/__init__.py
deepbench/astro_object/astro_object.py
deepbench/astro_object/galaxy_object.py
deepbench/astro_object/n_body_object.py
deepbench/astro_object/spiral_galaxy.py
deepbench/astro_object/star_object.py
deepbench/collection/__init__.py
deepbench/collection/collection.py
deepbench/collection/read_config.py
deepbench/collection/save.py
deepbench/image/__init__.py
deepbench/image/image.py
deepbench/image/shape_image.py
deepbench/image/sky_image.py
deepbench/physics_object/__init__.py
deepbench/physics_object/hamiltonian_pendulum.py
deepbench/physics_object/pendulum.py
deepbench/physics_object/physics_object.py
deepbench/settings/default_astro_object.yaml
deepbench/settings/default_physics_object.yaml
deepbench/settings/default_shapes.yaml
deepbench/settings/default_sky_object.yaml
deepbench/shapes/__init__.py
deepbench/shapes/shape_generator.py
deepbench-0.2.3.dist-info/WHEEL
deepbench-0.2.3.dist-info/LICENSE
deepbench-0.2.3.dist-info/METADATA
deepbench-0.2.3.dist-info/RECORD
