Metadata-Version: 2.1
Name: deepbench
Version: 0.2.3
Summary: Physics Benchmark Dataset Generator
Home-page: https://github.com/deepskies/DeepBench
License: Apache 2.0
Author: M. Voetberg
Author-email: maggiev@fnal.gov
Maintainer: M. Voetberg
Maintainer-email: maggiev@fnal.gov
Requires-Python: >=3.10,<4.0
Classifier: License :: Other/Proprietary License
Classifier: Programming Language :: Python :: 3
Classifier: Programming Language :: Python :: 3.10
Classifier: Programming Language :: Python :: 3.11
Requires-Dist: astropy (>=5.2.2,<6.0.0)
Requires-Dist: autograd (>=1.5,<2.0)
Requires-Dist: h5py (>=3.9.0)
Requires-Dist: matplotlib (>=3.7.1,<4.0.0)
Requires-Dist: numpy (>=1.25.0,<2.0.0)
Requires-Dist: pyyaml (>=6.0,<7.0)
Requires-Dist: scikit-image (>=0.23.0,<0.24.0)
Project-URL: Documentation, https://deepbench.readthedocs.io/en/latest/
Project-URL: Repository, https://github.com/deepskies/DeepBench
